rer.sitesearch-4.4.1-py3.10-nspkg.pth
rer/sitesearch/__init__.py
rer/sitesearch/configure.zcml
rer/sitesearch/setuphandlers.py
rer/sitesearch/testing.py
rer/sitesearch/upgrades.py
rer/sitesearch/upgrades.zcml
rer/sitesearch/utils.py
rer/sitesearch/vocabularies.py
rer/sitesearch/adapters/__init__.py
rer/sitesearch/adapters/configure.zcml
rer/sitesearch/adapters/custom_filters.py
rer/sitesearch/adapters/permission_checker.py
rer/sitesearch/browser/__init__.py
rer/sitesearch/browser/configure.zcml
rer/sitesearch/browser/controlpanel.py
rer/sitesearch/browser/i18n.py
rer/sitesearch/browser/interfaces.py
rer/sitesearch/browser/search.py
rer/sitesearch/browser/static/dist/prod/main.css
rer/sitesearch/browser/static/dist/prod/main.css.map
rer/sitesearch/browser/static/dist/prod/main.js
rer/sitesearch/browser/static/dist/prod/main.js.map
rer/sitesearch/browser/static/js/index.js
rer/sitesearch/browser/static/js/GroupsFilter/index.js
rer/sitesearch/browser/static/js/IndexesFilters/boolean.js
rer/sitesearch/browser/static/js/IndexesFilters/date.js
rer/sitesearch/browser/static/js/IndexesFilters/index.js
rer/sitesearch/browser/static/js/IndexesFilters/select.js
rer/sitesearch/browser/static/js/LocationFilter/index.js
rer/sitesearch/browser/static/js/SearchContainer/index.js
rer/sitesearch/browser/static/js/SearchFilters/index.js
rer/sitesearch/browser/static/js/SearchResults/header.js
rer/sitesearch/browser/static/js/SearchResults/index.js
rer/sitesearch/browser/static/js/SearchResults/pagination.js
rer/sitesearch/browser/static/js/SearchResults/ResultItem/Bando.js
rer/sitesearch/browser/static/js/SearchResults/ResultItem/DateAndPosition.js
rer/sitesearch/browser/static/js/SearchResults/ResultItem/ResultItem.js
rer/sitesearch/browser/static/js/SearchableTextFilter/index.js
rer/sitesearch/browser/static/js/SpecificFilters/SpecificFilter.js
rer/sitesearch/browser/static/js/SpecificFilters/index.js
rer/sitesearch/browser/static/js/utils/apiFetch.js
rer.sitesearch-4.4.1.dist-info/METADATA
rer.sitesearch-4.4.1.dist-info/WHEEL
rer.sitesearch-4.4.1.dist-info/entry_points.txt
rer.sitesearch-4.4.1.dist-info/namespace_packages.txt
rer.sitesearch-4.4.1.dist-info/top_level.txt
rer.sitesearch-4.4.1.dist-info/RECORD
