Metadata-Version: 2.1
Name: rer.sitesearch
Version: 4.4.1
Summary: A product that change the base site search of Plone with some new features.
Home-page: https://github.com/RegioneER/rer.sitesearch
Author: RedTurtle Technology
Author-email: sviluppo@redturtle.it
License: GPL version 2
Project-URL: PyPI, https://pypi.python.org/pypi/rer.sitesearch
Project-URL: Source, https://github.com/RegioneER/rer.sitesearch
Project-URL: Tracker, https://github.com/RegioneER/rer.sitesearch/issues
Keywords: Python Plone Search
Classifier: Development Status :: 5 - Production/Stable
Classifier: Framework :: Plone :: 5.1
Classifier: Framework :: Plone :: 5.2
Classifier: Framework :: Plone :: Addon
Classifier: Framework :: Plone
Classifier: Programming Language :: Python :: 2.7
Classifier: Programming Language :: Python :: 3.7
Classifier: Programming Language :: Python
Requires-Dist: setuptools
Requires-Dist: plone.api >=1.8.4
Requires-Dist: plone.restapi
Requires-Dist: plone.app.dexterity
Requires-Dist: collective.z3cform.jsonwidget
Provides-Extra: test
Requires-Dist: plone.app.testing ; extra == 'test'
Requires-Dist: plone.testing >=5.0.0 ; extra == 'test'
Requires-Dist: plone.app.contenttypes ; extra == 'test'
Requires-Dist: plone.app.robotframework[debug] ; extra == 'test'
Requires-Dist: collective.MockMailHost ; extra == 'test'
